text_to_ascii/__init__.py
text_to_ascii/main.py
text_to_ascii-0.4.dist-info/METADATA
text_to_ascii-0.4.dist-info/WHEEL
text_to_ascii-0.4.dist-info/entry_points.txt
text_to_ascii-0.4.dist-info/top_level.txt
text_to_ascii-0.4.dist-info/RECORD
